HealthTools/Ver_arterial_pression.py
HealthTools/__init__.py
HealthTools/calcular_debito_cardiaco.py
HealthTools/calcular_debito_urinario.py
HealthTools/calcular_fcm.py
HealthTools/calcular_frequencia_respiratoria.py
HealthTools/calcular_indice_apgar.py
HealthTools/calcular_tfg.py
HealthTools/calcular_tp.py
HealthTools/calcular_ttpa.py
HealthTools/classifica_capacidade_anaerobica.py
HealthTools/classifica_saturacao_spo2.py
HealthTools/classifica_tireoidiana.py
HealthTools/classificar_espirometria.py
HealthTools/classificar_glicemia.py
HealthTools/classificar_pvc.py
HealthTools/contar_hemacias.py
HealthTools/contar_leucocitos.py
HealthTools/contar_plaquetas.py
HealthTools/help.py
HealthTools/teste_funcao_hepatica.py
HealthTools/teste_funcao_renal.py
HealthTools/verifica_imc.py
Health_Tools-0.0.6.dist-info/METADATA
Health_Tools-0.0.6.dist-info/WHEEL
Health_Tools-0.0.6.dist-info/top_level.txt
Health_Tools-0.0.6.dist-info/RECORD
