Metadata-Version: 2.1
Name: Health_Tools
Version: 0.0.6
Summary: Ajuda com análise de resultados médicos e laboratoriais.
Author: Kawan S. Dias
Author-email: <kawan.dias@ufpi.edu.br>
Keywords: python,Medical,Data,analysis,simple,health-tools
Classifier: Development Status :: 1 - Planning
Classifier: Intended Audience :: Developers
Classifier: Programming Language :: Python :: 3
Classifier: Operating System :: Unix
Classifier: Operating System :: MacOS :: MacOS X
Classifier: Operating System :: Microsoft :: Windows
